[
     {
          "id":"41",
          "keyCode":"ESCAPE",
          "comment":"scape"
     },
     {
          "id":"58",
          "keyCode":"F1",
          "comment":"f1"
     },
     {
          "id":"59",
          "keyCode":"F2",
          "comment":"f2"
     },
     {
          "id":"60",
          "keyCode":"F3",
          "comment":"f3"
     },
     {
          "id":"61",
          "keyCode":"F4",
          "comment":"f4"
     },
     {
          "id":"62",
          "keyCode":"F5",
          "comment":"f5"
     },
     {
          "id":"63",
          "keyCode":"F6",
          "comment":"f6"
     },
     {
          "id":"64",
          "keyCode":"F7",
          "comment":"f7"
     },
     {
          "id":"65",
          "keyCode":"F8",
          "comment":"F8"
     },
     {
          "id":"66",
          "keyCode":"F9",
          "comment":"F9"
     },
     {
          "id":"67",
          "keyCode":"F10",
          "comment":"F10"
     },
     {
          "id":"68",
          "keyCode":"F11",
          "comment":"F11"
     },
     {
          "id":"69",
          "keyCode":"F12",
          "comment":"F12"
     },
     {
          "id":"49",
          "keyCode":"BACKSLASH",
          "comment":"\\"
     },
     {
          "id":"30",
          "keyCode":"ONE",
          "comment":"1 !"
     },
     {
          "id":"31",
          "keyCode":"TWO",
          "comment":"2"
     },
     {
          "id":"32",
          "keyCode":"THREE",
          "comment":"3"
     },
     {
          "id":"33",
          "keyCode":"FOUR",
          "comment":"4"
     },
     {
          "id":"34",
          "keyCode":"FIVE",
          "comment":"5"
     },
     {
          "id":"35",
          "keyCode":"SIX",
          "comment":"6"
     },
     {
          "id":"36",
          "keyCode":"SEVEN",
          "comment":"7"
     },
     {
          "id":"37",
          "keyCode":"EIGTH",
          "comment":"8"
     },
     {
          "id":"38",
          "keyCode":"NINE",
          "comment":"9"
     },
     {
          "id":"39",
          "keyCode":"ZERO",
          "comment":"0"
     },
     {
          "id":"56",
          "keyCode":"FORWARD_SLASH",
          "comment":"/"
     },
     {
          "id":"42",
          "keyCode":"BACKSPACE",
          "comment":"del <-"
     },
     {
          "id":"43",
          "keyCode":"TAB",
          "comment":"<- ->"
     },
     {
          "id":"20",
          "keyCode":"Q",
          "comment":"qQ"
     },
     {
          "id":"26",
          "keyCode":"W",
          "comment":"wW"
     },
     {
          "id":"8",
          "keyCode":"E",
          "comment":"eE"
     },
     {
          "id":"21",
          "keyCode":"R",
          "comment":"rR"
     },
     {
          "id":"23",
          "keyCode":"T",
          "comment":"tT"
     },
     {
          "id":"28",
          "keyCode":"Y",
          "comment":"yY"
     },
     {
          "id":"24",
          "keyCode":"U",
          "comment":"uU"
     },
     {
          "id":"12",
          "keyCode":"I",
          "comment":"uU"
     },
     {
          "id":"18",
          "keyCode":"O",
          "comment":"oO"
     },
     {
          "id":"19",
          "keyCode":"P",
          "comment":"pP"
     },
     {
          "id":"47",
          "keyCode":"LEFT_BRACKET",
          "comment":"´{"
     },
     {
          "id":"40",
          "keyCode":"RETURN",
          "comment":"enter"
     },
     {
          "id":"57",
          "keyCode":"CAPS_LOCK",
          "comment":"Bloq. mayus"
     },
     {
          "id":"4",
          "keyCode":"A",
          "comment":"aA"
     },
     {
          "id":"22",
          "keyCode":"S",
          "comment":"sS"
     },
     {
          "id":"7",
          "keyCode":"D",
          "comment":"dD"
     },
     {
          "id":"9",
          "keyCode":"F",
          "comment":"fF"
     },
     {
          "id":"10",
          "keyCode":"G",
          "comment":"gG"
     },
     {
          "id":"11",
          "keyCode":"H",
          "comment":"hH"
     },
     {
          "id":"13",
          "keyCode":"J",
          "comment":"jJ"
     },
     {
          "id":"14",
          "keyCode":"K",
          "comment":"kK"
     },
     {
          "id":"15",
          "keyCode":"L",
          "comment":"lL"
     },
     {
          "id":"47",
          "keyCode":"LEFT_BRACKET",
          "comment":"[`"
     },
     {
          "id":"48",
          "keyCode":"RIGHT_BRACKET",
          "comment":"]+"
     },
     {
          "id":"226",
          "keyCode":"ALT",
          "comment":"left alt"
     },
     {
          "id":"29",
          "keyCode":"Z",
          "comment":"zZ"
     },
     {
          "id":"27",
          "keyCode":"X",
          "comment":"xX"
     },
     {
          "id":"6",
          "keyCode":"C",
          "comment":"cC"
     },
     {
          "id":"25",
          "keyCode":"V",
          "comment":"vV"
     },
     {
          "id":"5",
          "keyCode":"B",
          "comment":"bB"
     },
     {
          "id":"17",
          "keyCode":"N",
          "comment":"nN"
     },
     {
          "id":"16",
          "keyCode":"M",
          "comment":"mM"
     },
     {
          "id":"54",
          "keyCode":"COMMA",
          "comment":","
     },
     {
          "id":"55",
          "keyCode":"PERIOD",
          "comment":"."
     },
     {
          "id":"45",
          "keyCode":"MINUS",
          "comment":"-_"
     },
     {
          "id":"229",
          "keyCode":"RIGHT_SHIFT",
          "comment":"shift ->"
     },
     {
          "id":"224",
          "keyCode":"CONTROL",
          "comment":"left control"
     },
     {
          "id":"227",
          "keyCode":"GUI",
          "comment":"windows button"
     },
     {
          "id":"226",
          "keyCode":"LEFT_ALT",
          "comment":"left alt"
     },
     {
          "id":"44",
          "keyCode":"SPACE",
          "comment":" --- "
     },
     {
          "id":"230",
          "keyCode":"RIGHT_ALT_CODE",
          "comment":"ALTGR"
     },
     {
          "id":"101",
          "keyCode":"APPLICATION",
          "comment":"MENU"
     },
     {
          "id":"228",
          "keyCode":"RIGHT_CONTROL",
          "comment":"right control"
     },
     {
          "id":"70",
          "keyCode":"PRINT_SCREEN",
          "comment":"impr pant"
     },
     {
          "id":"71",
          "keyCode":"SCROLL_LOCK",
          "comment":"scrLk"
     },
     {
          "id":"72",
          "keyCode":"PAUSE",
          "comment":"pause"
     },
     {
          "id":"73",
          "keyCode":"INSERT",
          "comment":"insert"
     },
     {
          "id":"74",
          "keyCode":"HOME",
          "comment":"home"
     },
     {
          "id":"75",
          "keyCode":"PAGE_UP",
          "comment":"PAGE UP"
     },
     {
          "id":"76",
          "keyCode":"DELETE",
          "comment":"delete ->"
     },
     {
          "id":"77",
          "keyCode":"END",
          "comment":"end"
     },
     {
          "id":"78",
          "keyCode":"PAGE_DOWN",
          "comment":"PAGE DOWN"
     },
     {
          "id":"82",
          "keyCode":"UP_ARROW",
          "comment":"UP ARROW"
     },
     {
          "id":"80",
          "keyCode":"LEFT_ARROW",
          "comment":"LEFT ARROW"
     },
     {
          "id":"81",
          "keyCode":"DOWN_ARROW",
          "comment":"DOWN ARROW"
     },
     {
          "id":"79",
          "keyCode":"RIGHT_ARROW",
          "comment":"RIGHT ARROW"
     }
]
